seekerfree/__init__.py
seekerfree/seekerfree.cpython-310-aarch64-linux.so
seekerfree/seekerfree.cpython-310-linux.so
seekerfree/seekerfree.cpython-311-aarch64-linux.so
seekerfree/seekerfree.cpython-311-linux.so
seekerfree/seekerfree.cpython-38-aarch64-linux.so
seekerfree/seekerfree.cpython-38-linux.so
seekerfree/seekerfree.cpython-39-aarch64-linux.so
seekerfree/seekerfree.cpython-39-linux.so
seekerfree/seekerfree.py
seekerfree/bin/coll
seekerfree/bin/coll-linux
seekerfree/scripts/darwin_seekeragg.sh
seekerfree/scripts/seekeragg.sh
insideopt_nextmv-0.0.10.dist-info/AUTHORS.rst
insideopt_nextmv-0.0.10.dist-info/LICENSE.rst
insideopt_nextmv-0.0.10.dist-info/METADATA
insideopt_nextmv-0.0.10.dist-info/WHEEL
insideopt_nextmv-0.0.10.dist-info/top_level.txt
insideopt_nextmv-0.0.10.dist-info/RECORD
